pqt/__init__.py
pqt/count.py
pqt/summary.py
pqt-0.0.2.dist-info/LICENSE
pqt-0.0.2.dist-info/METADATA
pqt-0.0.2.dist-info/WHEEL
pqt-0.0.2.dist-info/entry_points.txt
pqt-0.0.2.dist-info/top_level.txt
pqt-0.0.2.dist-info/RECORD
